ccdot/__init__.py
ccdot/ccdot.py
ccdot-0.1.dist-info/LICENSE
ccdot-0.1.dist-info/METADATA
ccdot-0.1.dist-info/WHEEL
ccdot-0.1.dist-info/top_level.txt
ccdot-0.1.dist-info/RECORD
